gatherup/__init__.py
gatherup/__main__.py
gatherup/gatherup.py
gatherup/data/__init__.py
gatherup/data/config.yaml
gatherup/data/project_details.txt
gatherup/example_files/__init__.py
gatherup/example_files/example_config_1.json
gatherup/example_files/log_with_traceback.log
gatherup/example_files/log_without_traceback.log
gatherup/gatherup.egg-info/SOURCES.txt
gatherup/gatherup.egg-info/dependency_links.txt
gatherup/gatherup.egg-info/requires.txt
gatherup/gatherup.egg-info/top_level.txt
gatherup/instructions/__init__.py
gatherup/instructions/instructions_de.txt
gatherup/instructions/instructions_en.txt
gatherup/instructions/instructions_fr.txt
gatherup/instructions/instructions_hi.txt
gatherup/instructions/instructions_raw.txt
gatherup-0.0.4.dist-info/LICENSE.txt
gatherup-0.0.4.dist-info/METADATA
gatherup-0.0.4.dist-info/WHEEL
gatherup-0.0.4.dist-info/entry_points.txt
gatherup-0.0.4.dist-info/top_level.txt
gatherup-0.0.4.dist-info/RECORD
