Metadata-Version: 2.1
Name: gatherup
Version: 0.0.4
Summary: Helps you post essential Python config details to GitHub or Discourse, all beautifully formatted
Home-page: https://github.com/nmstoker/gatherup
Author: Neil Stoker
Author-email: nstoker001@gmail.com
License: UNKNOWN
Platform: UNKNOWN
Classifier: Development Status :: 3 - Alpha
Classifier: Environment :: Console
Classifier: Intended Audience :: Developers
Classifier: License :: OSI Approved :: MIT License
Classifier: Natural Language :: English
Classifier: Operating System :: POSIX :: Linux
Classifier: Programming Language :: Python :: 3
Classifier: Programming Language :: Python :: 3.6
Classifier: Programming Language :: Python :: 3.7
Classifier: Programming Language :: Python :: 3.8
Classifier: License :: OSI Approved :: MIT License
Classifier: Operating System :: OS Independent
Classifier: Topic :: Software Development
Requires-Dist: click (<8.0,>7.0)
Requires-Dist: questionary (<2.0,>1.5.2)
Requires-Dist: rich (<9.0,>7.1)
Requires-Dist: confuse (<1.4,>1.2)
Requires-Dist: importlib-resources ; python_version < "3.7"
Provides-Extra: dev
Requires-Dist: pytest (>3.7) ; extra == 'dev'
